vasuSTT/__init__.py
vasustt-0.1.3.dist-info/METADATA
vasustt-0.1.3.dist-info/WHEEL
vasustt-0.1.3.dist-info/top_level.txt
vasustt-0.1.3.dist-info/RECORD
