Metadata-Version: 2.4
Name: vasuSTT
Version: 0.1.3
Summary: A simple STT module for JARVIS
Author: Vasu
Classifier: Programming Language :: Python :: 3
Classifier: Operating System :: OS Independent
Requires-Python: >=3.6
Requires-Dist: speechrecognition
Requires-Dist: selenium
Dynamic: author
Dynamic: classifier
Dynamic: description
Dynamic: description-content-type
Dynamic: requires-dist
Dynamic: requires-python
Dynamic: summary
